odoo/addons/mrp_workorder_update_component/README.rst
odoo/addons/mrp_workorder_update_component/__init__.py
odoo/addons/mrp_workorder_update_component/__manifest__.py
odoo/addons/mrp_workorder_update_component/i18n/it.po
odoo/addons/mrp_workorder_update_component/i18n/mrp_workorder_update_component.pot
odoo/addons/mrp_workorder_update_component/models/__init__.py
odoo/addons/mrp_workorder_update_component/models/mrp_workorder.py
odoo/addons/mrp_workorder_update_component/readme/CONTRIBUTORS.rst
odoo/addons/mrp_workorder_update_component/readme/DESCRIPTION.rst
odoo/addons/mrp_workorder_update_component/static/description/icon.png
odoo/addons/mrp_workorder_update_component/static/description/index.html
odoo/addons/mrp_workorder_update_component/tests/__init__.py
odoo/addons/mrp_workorder_update_component/tests/test_mrp_workorder.py
odoo/addons/mrp_workorder_update_component/views/mrp_workorder_view.xml
odoo/addons/mrp_workorder_update_component/wizards/__init__.py
odoo/addons/mrp_workorder_update_component/wizards/mrp_workorder_new_line.py
odoo/addons/mrp_workorder_update_component/wizards/mrp_workorder_new_line_view.xml
odoo13_addon_mrp_workorder_update_component-13.0.1.0.1.dev5.dist-info/METADATA
odoo13_addon_mrp_workorder_update_component-13.0.1.0.1.dev5.dist-info/WHEEL
odoo13_addon_mrp_workorder_update_component-13.0.1.0.1.dev5.dist-info/top_level.txt
odoo13_addon_mrp_workorder_update_component-13.0.1.0.1.dev5.dist-info/RECORD
